daWUAP/__init__.py
daWUAP/hyena.py
daWUAP/assimilation/__init__.py
daWUAP/assimilation/kalmanfilter.py
daWUAP/econengine/__init__.py
daWUAP/econengine/econfuncs.py
daWUAP/econengine/water_user.py
daWUAP/hydroengine/__init__.py
daWUAP/hydroengine/aux_models.py
daWUAP/hydroengine/hydroengine.py
daWUAP/hydroengine/rrmodels.py
daWUAP/plotting/__init__.py
daWUAP/plotting/plot_ensemble.py
daWUAP/utils/__init__.py
daWUAP/utils/assimilation.py
daWUAP/utils/check_farms.py
daWUAP/utils/coupling.py
daWUAP/utils/crop_coefficient.py
daWUAP/utils/exim_funcs.py
daWUAP/utils/fixtures.py
daWUAP/utils/io.py
daWUAP/utils/raster.py
daWUAP/utils/utilsAssimilation.py
daWUAP/utils/utilsOutputs.py
daWUAP/utils/utilsRaster.py
daWUAP/utils/utilsVector.py
daWUAP/utils/vector.py
daWUAP-0.3.0.dev0.data/scripts/dataCollectionThredds.py
daWUAP-0.3.0.dev0.data/scripts/hyena.py
daWUAP-0.3.0.dev0.data/scripts/writeRasterModelParameters.py
daWUAP-0.3.0.dev0.data/scripts/writeVectorModelParameters.py
daWUAP-0.3.0.dev0.dist-info/LICENSE
daWUAP-0.3.0.dev0.dist-info/METADATA
daWUAP-0.3.0.dev0.dist-info/WHEEL
daWUAP-0.3.0.dev0.dist-info/top_level.txt
daWUAP-0.3.0.dev0.dist-info/RECORD
