Metadata-Version: 2.1
Name: daWUAP
Version: 0.3.0.dev0
Summary: Hydrologic Engine for daWUAP model
Home-page: https://bitbucket.org/umthydromodeling/dawuaphydroengine
Author: Marco Maneta
Author-email: marco.maneta@umontana.edu
License: UNKNOWN
Download-URL: https://bitbucket.org/umthydromodeling/dawuaphydroengine/get/a88ac8f68b01.zip
Platform: UNKNOWN
Requires-Dist: matplotlib
Requires-Dist: numpy
Requires-Dist: rasterio
Requires-Dist: rasterstats
Requires-Dist: fiona
Requires-Dist: shapely
Requires-Dist: tqdm
Requires-Dist: scipy
Requires-Dist: pandas
Requires-Dist: tables
Requires-Dist: fire
Provides-Extra: test
Requires-Dist: nose ; extra == 'test'
Requires-Dist: mock ; extra == 'test'
